currencyapinet/__init__.py
currencyapinet/currency.py
currencyapinet/endpoints/__init__.py
currencyapinet/endpoints/convert.py
currencyapinet/endpoints/currencies.py
currencyapinet/endpoints/endpoint.py
currencyapinet/endpoints/history.py
currencyapinet/endpoints/rates.py
currencyapinet/endpoints/timeframe.py
tests/__init__.py
tests/test_currency.py
tests/endpoints/__init__.py
tests/endpoints/test_convert.py
tests/endpoints/test_currencies.py
tests/endpoints/test_endpoint.py
tests/endpoints/test_history.py
tests/endpoints/test_rates.py
tests/endpoints/test_timeframe.py
currencyapinet-1.0.4.dist-info/LICENSE
currencyapinet-1.0.4.dist-info/METADATA
currencyapinet-1.0.4.dist-info/WHEEL
currencyapinet-1.0.4.dist-info/top_level.txt
currencyapinet-1.0.4.dist-info/RECORD
