Metadata-Version: 2.1
Name: currencyapinet
Version: 1.0.4
Summary: Python wrapper for CurrencyApi.net
Home-page: https://currencyapi.net/sdk/python
Author-email: support@currencyapi.net
Keywords: currency feed,currency rates,currencyapi,currency
Classifier: License :: OSI Approved :: MIT License
Classifier: Intended Audience :: Developers
Classifier: Programming Language :: Python :: 3 :: Only
Classifier: Topic :: Software Development :: Libraries :: Python Modules
License-File: LICENSE
Requires-Dist: requests
